<?xml version='1.0' encoding='UTF-8' ?>
<?charles serialisation-version='2.0' ?>
<rewriteSet-array>
  <rewriteSet>
    <active>true</active>
    <name>Homework</name>
    <hosts>
      <locationPatterns>
        <locationMatch>
          <location>
            <protocol>http</protocol>
            <host>162.55.220.72</host>
            <port>5005</port>
            <path>/get_method</path>
          </location>
          <enabled>true</enabled>
        </locationMatch>
        <locationMatch>
          <location>
            <protocol>http</protocol>
            <host>162.55.220.72</host>
            <port>5005</port>
            <path>/user_info_3</path>
          </location>
          <enabled>true</enabled>
        </locationMatch>
        <locationMatch>
          <location>
            <protocol>http</protocol>
            <host>162.55.220.72</host>
            <port>5005</port>
            <path>/object_info_1</path>
            <query>name=Melissa&amp;weight=175&amp;age=19</query>
          </location>
          <enabled>true</enabled>
        </locationMatch>
        <locationMatch>
          <location>
            <protocol>http</protocol>
            <host>162.55.220.72</host>
            <port>5005</port>
            <path>/object_info_3</path>
          </location>
          <enabled>true</enabled>
        </locationMatch>
        <locationMatch>
          <location>
            <protocol>http</protocol>
            <host>162.55.220.72</host>
            <port>5005</port>
            <path>/object_info_4</path>
          </location>
          <enabled>true</enabled>
        </locationMatch>
        <locationMatch>
          <location>
            <protocol>http</protocol>
            <host>162.55.220.72</host>
            <port>5005</port>
            <path>/user_info_2</path>
          </location>
          <enabled>true</enabled>
        </locationMatch>
      </locationPatterns>
    </hosts>
    <rules>
      <rewriteRule>
        <active>true</active>
        <ruleType>6</ruleType>
        <matchValue> Alex</matchValue>
        <matchHeaderRegex>false</matchHeaderRegex>
        <matchValueRegex>false</matchValueRegex>
        <matchRequest>false</matchRequest>
        <matchResponse>false</matchResponse>
        <newValue>Marcin</newValue>
        <newHeaderRegex>false</newHeaderRegex>
        <newValueRegex>false</newValueRegex>
        <matchWholeValue>false</matchWholeValue>
        <caseSensitive>false</caseSensitive>
        <replaceType>2</replaceType>
      </rewriteRule>
      <rewriteRule>
        <active>true</active>
        <ruleType>7</ruleType>
        <matchValue>4000</matchValue>
        <matchHeaderRegex>false</matchHeaderRegex>
        <matchValueRegex>false</matchValueRegex>
        <matchRequest>true</matchRequest>
        <matchResponse>false</matchResponse>
        <newValue>3500</newValue>
        <newHeaderRegex>false</newHeaderRegex>
        <newValueRegex>false</newValueRegex>
        <matchWholeValue>false</matchWholeValue>
        <caseSensitive>false</caseSensitive>
        <replaceType>2</replaceType>
      </rewriteRule>
      <rewriteRule>
        <active>true</active>
        <ruleType>7</ruleType>
        <matchValue>&quot;name&quot;: &quot;Melissa&quot;</matchValue>
        <matchHeaderRegex>false</matchHeaderRegex>
        <matchValueRegex>false</matchValueRegex>
        <matchRequest>false</matchRequest>
        <matchResponse>true</matchResponse>
        <newValue>&quot;name&quot;: &quot;Nicol&quot;</newValue>
        <newHeaderRegex>false</newHeaderRegex>
        <newValueRegex>false</newValueRegex>
        <matchWholeValue>false</matchWholeValue>
        <caseSensitive>false</caseSensitive>
        <replaceType>2</replaceType>
      </rewriteRule>
      <rewriteRule>
        <active>true</active>
        <ruleType>7</ruleType>
        <matchValue>&quot;daily_food&quot;: 2.1</matchValue>
        <matchHeaderRegex>false</matchHeaderRegex>
        <matchValueRegex>false</matchValueRegex>
        <matchRequest>false</matchRequest>
        <matchResponse>true</matchResponse>
        <newValue>&quot;daily_food&quot;: 180</newValue>
        <newHeaderRegex>false</newHeaderRegex>
        <newValueRegex>false</newValueRegex>
        <matchWholeValue>false</matchWholeValue>
        <caseSensitive>false</caseSensitive>
        <replaceType>2</replaceType>
      </rewriteRule>
      <rewriteRule>
        <active>true</active>
        <ruleType>7</ruleType>
        <matchValue>&quot;daily_sleep&quot;: 437.5</matchValue>
        <matchHeaderRegex>false</matchHeaderRegex>
        <matchValueRegex>false</matchValueRegex>
        <matchRequest>false</matchRequest>
        <matchResponse>true</matchResponse>
        <newValue>&quot;daily_sleep&quot;: 120</newValue>
        <newHeaderRegex>false</newHeaderRegex>
        <newValueRegex>false</newValueRegex>
        <matchWholeValue>false</matchWholeValue>
        <caseSensitive>false</caseSensitive>
        <replaceType>2</replaceType>
      </rewriteRule>
      <rewriteRule>
        <active>true</active>
        <ruleType>11</ruleType>
        <matchValue>200</matchValue>
        <matchHeaderRegex>false</matchHeaderRegex>
        <matchValueRegex>false</matchValueRegex>
        <matchRequest>false</matchRequest>
        <matchResponse>false</matchResponse>
        <newValue>500</newValue>
        <newHeaderRegex>false</newHeaderRegex>
        <newValueRegex>false</newValueRegex>
        <matchWholeValue>false</matchWholeValue>
        <caseSensitive>false</caseSensitive>
        <replaceType>2</replaceType>
      </rewriteRule>
      <rewriteRule>
        <active>true</active>
        <ruleType>11</ruleType>
        <matchValue>200</matchValue>
        <matchHeaderRegex>false</matchHeaderRegex>
        <matchValueRegex>false</matchValueRegex>
        <matchRequest>false</matchRequest>
        <matchResponse>false</matchResponse>
        <newValue>405</newValue>
        <newHeaderRegex>false</newHeaderRegex>
        <newValueRegex>false</newValueRegex>
        <matchWholeValue>false</matchWholeValue>
        <caseSensitive>false</caseSensitive>
        <replaceType>2</replaceType>
      </rewriteRule>
      <rewriteRule>
        <active>true</active>
        <ruleType>11</ruleType>
        <matchValue>200</matchValue>
        <matchHeaderRegex>false</matchHeaderRegex>
        <matchValueRegex>false</matchValueRegex>
        <matchRequest>false</matchRequest>
        <matchResponse>false</matchResponse>
        <newValue>405</newValue>
        <newHeaderRegex>false</newHeaderRegex>
        <newValueRegex>false</newValueRegex>
        <matchWholeValue>false</matchWholeValue>
        <caseSensitive>false</caseSensitive>
        <replaceType>2</replaceType>
      </rewriteRule>
      <rewriteRule>
        <active>true</active>
        <ruleType>9</ruleType>
        <matchHeader>salary</matchHeader>
        <matchValue>7000</matchValue>
        <matchHeaderRegex>false</matchHeaderRegex>
        <matchValueRegex>false</matchValueRegex>
        <matchRequest>false</matchRequest>
        <matchResponse>false</matchResponse>
        <newHeader>salary</newHeader>
        <newValue>12000</newValue>
        <newHeaderRegex>false</newHeaderRegex>
        <newValueRegex>false</newValueRegex>
        <matchWholeValue>false</matchWholeValue>
        <caseSensitive>false</caseSensitive>
        <replaceType>2</replaceType>
      </rewriteRule>
      <rewriteRule>
        <active>true</active>
        <ruleType>7</ruleType>
        <matchValue>24000</matchValue>
        <matchHeaderRegex>false</matchHeaderRegex>
        <matchValueRegex>false</matchValueRegex>
        <matchRequest>false</matchRequest>
        <matchResponse>true</matchResponse>
        <newValue>1</newValue>
        <newHeaderRegex>false</newHeaderRegex>
        <newValueRegex>false</newValueRegex>
        <matchWholeValue>false</matchWholeValue>
        <caseSensitive>false</caseSensitive>
        <replaceType>2</replaceType>
      </rewriteRule>
      <rewriteRule>
        <active>true</active>
        <ruleType>11</ruleType>
        <matchValue>200</matchValue>
        <matchHeaderRegex>false</matchHeaderRegex>
        <matchValueRegex>false</matchValueRegex>
        <matchRequest>false</matchRequest>
        <matchResponse>false</matchResponse>
        <newValue>405</newValue>
        <newHeaderRegex>false</newHeaderRegex>
        <newValueRegex>false</newValueRegex>
        <matchWholeValue>false</matchWholeValue>
        <caseSensitive>false</caseSensitive>
        <replaceType>2</replaceType>
      </rewriteRule>
      <rewriteRule>
        <active>true</active>
        <ruleType>7</ruleType>
        <matchValue>&quot;qa_salary_after_1.5_year&quot;</matchValue>
        <matchHeaderRegex>false</matchHeaderRegex>
        <matchValueRegex>false</matchValueRegex>
        <matchRequest>false</matchRequest>
        <matchResponse>true</matchResponse>
        <newValue>&quot;qa_salary_after_1.5_month&quot;</newValue>
        <newHeaderRegex>false</newHeaderRegex>
        <newValueRegex>false</newValueRegex>
        <matchWholeValue>false</matchWholeValue>
        <caseSensitive>false</caseSensitive>
        <replaceType>2</replaceType>
      </rewriteRule>
      <rewriteRule>
        <active>true</active>
        <ruleType>7</ruleType>
        <matchValue>5700.0</matchValue>
        <matchHeaderRegex>false</matchHeaderRegex>
        <matchValueRegex>false</matchValueRegex>
        <matchRequest>false</matchRequest>
        <matchResponse>true</matchResponse>
        <newValue>23</newValue>
        <newHeaderRegex>false</newHeaderRegex>
        <newValueRegex>false</newValueRegex>
        <matchWholeValue>false</matchWholeValue>
        <caseSensitive>false</caseSensitive>
        <replaceType>2</replaceType>
      </rewriteRule>
    </rules>
  </rewriteSet>
</rewriteSet-array>